dogbone/__init__.py
dogbone-0.0.0.dist-info/LICENSE
dogbone-0.0.0.dist-info/METADATA
dogbone-0.0.0.dist-info/WHEEL
dogbone-0.0.0.dist-info/top_level.txt
dogbone-0.0.0.dist-info/RECORD
