Metadata-Version: 2.1
Name: dogbone
Version: 0.0.0
Summary: Datadog compatible telemetry handler
License: MIT
Project-URL: Repository, https://github.com/whardier/dogbone-python
Classifier: Development Status :: 1 - Planning
Classifier: Intended Audience :: Developers
Classifier: Intended Audience :: Information Technology
Classifier: License :: OSI Approved :: MIT License
Classifier: Programming Language :: Python :: 3 :: Only
Classifier: Programming Language :: Python :: 3.7
Classifier: Programming Language :: Python :: 3.8
Classifier: Programming Language :: Python :: 3.9
Classifier: Programming Language :: Python :: 3.10
Classifier: Programming Language :: Python :: 3.11
Classifier: Programming Language :: Python :: 3
Classifier: Programming Language :: Python
Classifier: Topic :: Software Development :: Libraries :: Python Modules
Classifier: Topic :: Software Development :: Libraries
Requires-Python: <4.0,>=3.7
License-File: LICENSE
Provides-Extra: dev
Requires-Dist: black (~=22.10) ; extra == 'dev'
Requires-Dist: build (~=0.9) ; extra == 'dev'
Requires-Dist: flake8 (~=5.0) ; extra == 'dev'
Requires-Dist: flake8-bandit (~=4.1) ; extra == 'dev'
Requires-Dist: flake8-bugbear (~=22.12) ; extra == 'dev'
Requires-Dist: flake8-builtins (~=2.0) ; extra == 'dev'
Requires-Dist: flake8-comprehensions (~=3.10) ; extra == 'dev'
Requires-Dist: flake8-eradicate (~=1.4) ; extra == 'dev'
Requires-Dist: flake8-isort (~=5.0) ; extra == 'dev'
Requires-Dist: flake8-plugin-utils (~=1.3) ; extra == 'dev'
Requires-Dist: flake8-print (~=5.0) ; extra == 'dev'
Requires-Dist: flake8-pyproject (~=1.2) ; extra == 'dev'
Requires-Dist: flake8-requirements (~=1.7) ; extra == 'dev'
Requires-Dist: flake8-return (~=1.2) ; extra == 'dev'
Requires-Dist: flake8-use-pathlib (~=0.3) ; extra == 'dev'
Requires-Dist: mccabe (~=0.7) ; extra == 'dev'
Requires-Dist: mypy (~=0.991) ; extra == 'dev'
Requires-Dist: pre-commit (~=2.20) ; extra == 'dev'
Requires-Dist: pytest (~=7.2) ; extra == 'dev'
Requires-Dist: tox (~=3.27) ; extra == 'dev'
Requires-Dist: twine (~=4.0) ; extra == 'dev'
